pyatproto/__init__.py
pyatproto/atproto.py
pyatproto-0.2.0.dist-info/LICENSE
pyatproto-0.2.0.dist-info/METADATA
pyatproto-0.2.0.dist-info/WHEEL
pyatproto-0.2.0.dist-info/top_level.txt
pyatproto-0.2.0.dist-info/RECORD
