Metadata-Version: 2.1
Name: pyatproto
Version: 0.2.0
Summary: A wrapper for interacting with the AT Protocol API.
Home-page: https://github.com/capjamesg/pyatproto
Author: capjamesg
Author-email: jamesg@jamesg.blog
Project-URL: Bug Tracker, https://github.com/capjamesg/pyatproto/issues
Classifier: Programming Language :: Python :: 3
Classifier: License :: OSI Approved :: MIT License
Classifier: Operating System :: OS Independent
Requires-Python: >=3.6
License-File: LICENSE
